django_rok/__init__.py
django_rok/re_forward_port.py
django_rok/ssh_tunnel.py
django_rok/util.py
django_rok/views.py
django_rok/management/__init__.py
django_rok/management/commands/__init__.py
django_rok/management/commands/runrok.py
django_rok-1.0.dist-info/METADATA
django_rok-1.0.dist-info/RECORD
django_rok-1.0.dist-info/WHEEL
django_rok-1.0.dist-info/top_level.txt
