Metadata-Version: 2.1
Name: django-rok
Version: 1.0
Summary: Public url for your local web server.
Home-page: https://github.com/droidlife/django-rok
Author: Ankur Jain
Author-email: ankurj630@gmail.com
License: MIT
Platform: UNKNOWN
Classifier: Environment :: Web Environment
Classifier: Framework :: Django
Classifier: Intended Audience :: Developers
Classifier: License :: OSI Approved :: MIT License
Classifier: Operating System :: OS Independent
Classifier: Programming Language :: Python
Classifier: Programming Language :: Python :: 2.7
Classifier: Programming Language :: Python :: 3.5
Requires-Dist: paramiko (>=2.4.1)
